csmc/__init__.py
csmc/adaptive_mc/__init__.py
csmc/adaptive_mc/asmc.py
csmc/adaptive_mc/mc2.py
csmc/csmc.py
csmc/css.py
csmc/errors/__init__.py
csmc/errors/errors.py
csmc/mc/__init__.py
csmc/mc/cgm.py
csmc/mc/nn_completion.py
csmc/mc/soft_impute.py
csmc/mc_sota/__init__.py
csmc/mc_sota/curplus.py
csmc/mc_sota/sgd.py
csmc/mc_sota/svp.py
csmc/settings.py
csmc/transform.py
csmc-2.0.0.dist-info/LICENSE
csmc-2.0.0.dist-info/WHEEL
csmc-2.0.0.dist-info/METADATA
csmc-2.0.0.dist-info/RECORD
